{
  "updatedAt": "2026-02-18T04:00:47.533Z",
  "createdAt": "2026-02-18T04:00:47.533Z",
  "id": "XUmbIpT6vJpWwvge",
  "name": "[BATCH] Generate Plan Videos",
  "active": true,
  "isArchived": false,
  "nodes": [
    {
      "id": "webhook-trigger",
      "name": "Webhook Trigger",
      "type": "n8n-nodes-base.webhook",
      "typeVersion": 2,
      "position": [
        250,
        300
      ],
      "webhookId": "generate-videos",
      "parameters": {
        "path": "generate-videos",
        "httpMethod": "POST",
        "responseMode": "responseNode"
      }
    },
    {
      "id": "manual-trigger",
      "name": "Manual Trigger",
      "type": "n8n-nodes-base.manualTrigger",
      "typeVersion": 1,
      "position": [
        250,
        500
      ],
      "parameters": {}
    },
    {
      "id": "get-plan-assets",
      "name": "Get Plan Assets",
      "type": "n8n-nodes-base.postgres",
      "typeVersion": 2.5,
      "position": [
        500,
        300
      ],
      "parameters": {
        "operation": "executeQuery",
        "query": "SELECT \n  a.id AS asset_id,\n  a.asset_type,\n  a.template_name,\n  a.avatar_id,\n  a.background_id,\n  a.placements,\n  a.script_text,\n  wp.client_id,\n  wp.theme_name,\n  wp.status AS plan_status,\n  c.name AS client_name,\n  c.slug AS client_slug\nFROM assets a\nJOIN weekly_plans wp ON a.plan_id = wp.id\nJOIN clients c ON wp.client_id = c.id\nWHERE a.plan_id = '{{ $json.body.plan_id }}'::uuid\n  AND a.included = true\n  AND (a.asset_type = 'video' OR a.asset_type IS NULL)"
      },
      "credentials": {
        "postgres": {
          "id": "ZUwzqy3kvUJpXrDM",
          "name": "Postgres (Dev)"
        }
      }
    },
    {
      "id": "has-video-assets",
      "name": "Has Video Assets?",
      "type": "n8n-nodes-base.if",
      "typeVersion": 2.2,
      "position": [
        700,
        300
      ],
      "parameters": {
        "conditions": {
          "options": {
            "caseSensitive": true,
            "leftValue": "",
            "typeValidation": "strict"
          },
          "conditions": [
            {
              "id": "condition-0",
              "leftValue": "={{ $json.asset_id }}",
              "rightValue": "",
              "operator": {
                "type": "string",
                "operation": "isNotEmpty",
                "singleValue": true
              }
            }
          ],
          "combinator": "and"
        }
      }
    },
    {
      "id": "build-job-payload",
      "name": "Build Job Payload",
      "type": "n8n-nodes-base.code",
      "typeVersion": 2,
      "position": [
        900,
        300
      ],
      "parameters": {
        "jsCode": "const items = $input.all();\nconst results = [];\n\nfor (const item of items) {\n  const d = item.json;\n  \n  // Parse placements to determine ratios and platforms\n  let ratios = ['9:16']; // default\n  let platforms = ['meta'];\n  \n  if (d.placements) {\n    const p = typeof d.placements === 'string' ? JSON.parse(d.placements) : d.placements;\n    const ratioSet = new Set();\n    const platSet = new Set();\n    \n    if (Array.isArray(p)) {\n      for (const placement of p) {\n        if (placement.included !== false) {\n          if (placement.ratio) ratioSet.add(placement.ratio);\n          if (placement.platform) platSet.add(placement.platform);\n        }\n      }\n    }\n    \n    if (ratioSet.size > 0) ratios = [...ratioSet];\n    if (platSet.size > 0) platforms = [...platSet];\n  }\n  \n  // Determine template_id from template_name\n  let template_id = 'multi-item'; // default\n  const tn = (d.template_name || '').toLowerCase();\n  if (tn.includes('spotlight')) template_id = 'spotlight';\n  else if (tn.includes('edu') || tn.includes('education')) template_id = 'educational';\n  else if (tn.includes('multi')) template_id = 'multi-item';\n  \n  results.push({\n    json: {\n      client_id: d.client_id,\n      asset_id: d.asset_id,\n      template_id: template_id,\n      avatar_id: d.avatar_id || null,\n      background_id: d.background_id || null,\n      ratios: ratios,\n      platforms: platforms,\n      email: 'system@ad-pilot.ai',\n      source: 'weekly_cycle',\n      client_name: d.client_name\n    }\n  });\n}\n\nreturn results;"
      }
    },
    {
      "id": "trigger-job-gateway",
      "name": "Trigger Job Gateway",
      "type": "n8n-nodes-base.httpRequest",
      "typeVersion": 4.2,
      "position": [
        1100,
        300
      ],
      "parameters": {
        "method": "POST",
        "url": "https://ad-pilot-n8n-development.up.railway.app/webhook/ad-pilot/start",
        "sendBody": true,
        "specifyBody": "json",
        "jsonBody": "={{ JSON.stringify({ client_id: $json.client_id, template_id: $json.template_id, avatar_id: $json.avatar_id, background_id: $json.background_id, ratios: $json.ratios, platforms: $json.platforms, email: $json.email, source: $json.source, asset_id: $json.asset_id }) }}",
        "options": {
          "response": {
            "response": {
              "neverError": true
            }
          }
        }
      }
    },
    {
      "id": "aggregate-results",
      "name": "Aggregate Results",
      "type": "n8n-nodes-base.aggregate",
      "typeVersion": 1,
      "position": [
        1300,
        300
      ],
      "parameters": {
        "aggregate": "aggregateAllItemData",
        "options": {}
      }
    },
    {
      "id": "format-response",
      "name": "Format Response",
      "type": "n8n-nodes-base.code",
      "typeVersion": 2,
      "position": [
        1500,
        300
      ],
      "parameters": {
        "jsCode": "const items = $input.all();\nconst allData = items[0]?.json?.data || [];\nconst jobs = allData.map(d => ({ asset_id: d.asset_id, job_id: d.job_id, status: d.status }));\n\nreturn [{\n  json: {\n    success: true,\n    message: `Triggered video generation for ${jobs.length} assets`,\n    jobs: jobs,\n    triggered_at: new Date().toISOString()\n  }\n}];"
      }
    },
    {
      "id": "respond",
      "name": "Respond",
      "type": "n8n-nodes-base.respondToWebhook",
      "typeVersion": 1.1,
      "position": [
        1700,
        300
      ],
      "parameters": {
        "respondWith": "json",
        "responseBody": "={{ $json }}"
      }
    },
    {
      "id": "no-assets-response",
      "name": "No Assets Response",
      "type": "n8n-nodes-base.respondToWebhook",
      "typeVersion": 1.1,
      "position": [
        900,
        500
      ],
      "parameters": {
        "respondWith": "json",
        "responseBody": "={{ { success: false, message: 'No video assets found for this plan' } }}"
      }
    }
  ],
  "connections": {
    "Webhook Trigger": {
      "main": [
        [
          {
            "node": "Get Plan Assets",
            "type": "main",
            "index": 0
          }
        ]
      ]
    },
    "Manual Trigger": {
      "main": [
        [
          {
            "node": "Get Plan Assets",
            "type": "main",
            "index": 0
          }
        ]
      ]
    },
    "Get Plan Assets": {
      "main": [
        [
          {
            "node": "Has Video Assets?",
            "type": "main",
            "index": 0
          }
        ]
      ]
    },
    "Has Video Assets?": {
      "main": [
        [
          {
            "node": "Build Job Payload",
            "type": "main",
            "index": 0
          }
        ],
        [
          {
            "node": "No Assets Response",
            "type": "main",
            "index": 0
          }
        ]
      ]
    },
    "Build Job Payload": {
      "main": [
        [
          {
            "node": "Trigger Job Gateway",
            "type": "main",
            "index": 0
          }
        ]
      ]
    },
    "Trigger Job Gateway": {
      "main": [
        [
          {
            "node": "Aggregate Results",
            "type": "main",
            "index": 0
          }
        ]
      ]
    },
    "Aggregate Results": {
      "main": [
        [
          {
            "node": "Format Response",
            "type": "main",
            "index": 0
          }
        ]
      ]
    },
    "Format Response": {
      "main": [
        [
          {
            "node": "Respond",
            "type": "main",
            "index": 0
          }
        ]
      ]
    }
  },
  "settings": {
    "executionOrder": "v1",
    "callerPolicy": "workflowsFromSameOwner",
    "availableInMCP": false
  },
  "staticData": null,
  "meta": null,
  "pinData": null,
  "versionId": "19009727-493b-4b9a-8ab6-e2c31a39abc1",
  "activeVersionId": "19009727-493b-4b9a-8ab6-e2c31a39abc1",
  "triggerCount": 1,
  "shared": [
    {
      "updatedAt": "2026-02-18T04:00:47.533Z",
      "createdAt": "2026-02-18T04:00:47.533Z",
      "role": "workflow:owner",
      "workflowId": "XUmbIpT6vJpWwvge",
      "projectId": "jfzY6AcGvieAQa3s"
    }
  ],
  "activeVersion": {
    "updatedAt": "2026-02-18T04:00:47.553Z",
    "createdAt": "2026-02-18T04:00:47.553Z",
    "versionId": "19009727-493b-4b9a-8ab6-e2c31a39abc1",
    "workflowId": "XUmbIpT6vJpWwvge",
    "nodes": [
      {
        "id": "webhook-trigger",
        "name": "Webhook Trigger",
        "type": "n8n-nodes-base.webhook",
        "typeVersion": 2,
        "position": [
          250,
          300
        ],
        "webhookId": "generate-videos",
        "parameters": {
          "path": "generate-videos",
          "httpMethod": "POST",
          "responseMode": "responseNode"
        }
      },
      {
        "id": "manual-trigger",
        "name": "Manual Trigger",
        "type": "n8n-nodes-base.manualTrigger",
        "typeVersion": 1,
        "position": [
          250,
          500
        ],
        "parameters": {}
      },
      {
        "id": "get-plan-assets",
        "name": "Get Plan Assets",
        "type": "n8n-nodes-base.postgres",
        "typeVersion": 2.5,
        "position": [
          500,
          300
        ],
        "parameters": {
          "operation": "executeQuery",
          "query": "SELECT \n  a.id AS asset_id,\n  a.asset_type,\n  a.template_name,\n  a.avatar_id,\n  a.background_id,\n  a.placements,\n  a.script_text,\n  wp.client_id,\n  wp.theme_name,\n  wp.status AS plan_status,\n  c.name AS client_name,\n  c.slug AS client_slug\nFROM assets a\nJOIN weekly_plans wp ON a.plan_id = wp.id\nJOIN clients c ON wp.client_id = c.id\nWHERE a.plan_id = '{{ $json.body.plan_id }}'::uuid\n  AND a.included = true\n  AND (a.asset_type = 'video' OR a.asset_type IS NULL)"
        },
        "credentials": {
          "postgres": {
            "id": "ZUwzqy3kvUJpXrDM",
            "name": "Postgres (Dev)"
          }
        }
      },
      {
        "id": "has-video-assets",
        "name": "Has Video Assets?",
        "type": "n8n-nodes-base.if",
        "typeVersion": 2.2,
        "position": [
          700,
          300
        ],
        "parameters": {
          "conditions": {
            "options": {
              "caseSensitive": true,
              "leftValue": "",
              "typeValidation": "strict"
            },
            "conditions": [
              {
                "id": "condition-0",
                "leftValue": "={{ $json.asset_id }}",
                "rightValue": "",
                "operator": {
                  "type": "string",
                  "operation": "isNotEmpty",
                  "singleValue": true
                }
              }
            ],
            "combinator": "and"
          }
        }
      },
      {
        "id": "build-job-payload",
        "name": "Build Job Payload",
        "type": "n8n-nodes-base.code",
        "typeVersion": 2,
        "position": [
          900,
          300
        ],
        "parameters": {
          "jsCode": "const items = $input.all();\nconst results = [];\n\nfor (const item of items) {\n  const d = item.json;\n  \n  // Parse placements to determine ratios and platforms\n  let ratios = ['9:16']; // default\n  let platforms = ['meta'];\n  \n  if (d.placements) {\n    const p = typeof d.placements === 'string' ? JSON.parse(d.placements) : d.placements;\n    const ratioSet = new Set();\n    const platSet = new Set();\n    \n    if (Array.isArray(p)) {\n      for (const placement of p) {\n        if (placement.included !== false) {\n          if (placement.ratio) ratioSet.add(placement.ratio);\n          if (placement.platform) platSet.add(placement.platform);\n        }\n      }\n    }\n    \n    if (ratioSet.size > 0) ratios = [...ratioSet];\n    if (platSet.size > 0) platforms = [...platSet];\n  }\n  \n  // Determine template_id from template_name\n  let template_id = 'multi-item'; // default\n  const tn = (d.template_name || '').toLowerCase();\n  if (tn.includes('spotlight')) template_id = 'spotlight';\n  else if (tn.includes('edu') || tn.includes('education')) template_id = 'educational';\n  else if (tn.includes('multi')) template_id = 'multi-item';\n  \n  results.push({\n    json: {\n      client_id: d.client_id,\n      asset_id: d.asset_id,\n      template_id: template_id,\n      avatar_id: d.avatar_id || null,\n      background_id: d.background_id || null,\n      ratios: ratios,\n      platforms: platforms,\n      email: 'system@ad-pilot.ai',\n      source: 'weekly_cycle',\n      client_name: d.client_name\n    }\n  });\n}\n\nreturn results;"
        }
      },
      {
        "id": "trigger-job-gateway",
        "name": "Trigger Job Gateway",
        "type": "n8n-nodes-base.httpRequest",
        "typeVersion": 4.2,
        "position": [
          1100,
          300
        ],
        "parameters": {
          "method": "POST",
          "url": "https://ad-pilot-n8n-development.up.railway.app/webhook/ad-pilot/start",
          "sendBody": true,
          "specifyBody": "json",
          "jsonBody": "={{ JSON.stringify({ client_id: $json.client_id, template_id: $json.template_id, avatar_id: $json.avatar_id, background_id: $json.background_id, ratios: $json.ratios, platforms: $json.platforms, email: $json.email, source: $json.source, asset_id: $json.asset_id }) }}",
          "options": {
            "response": {
              "response": {
                "neverError": true
              }
            }
          }
        }
      },
      {
        "id": "aggregate-results",
        "name": "Aggregate Results",
        "type": "n8n-nodes-base.aggregate",
        "typeVersion": 1,
        "position": [
          1300,
          300
        ],
        "parameters": {
          "aggregate": "aggregateAllItemData",
          "options": {}
        }
      },
      {
        "id": "format-response",
        "name": "Format Response",
        "type": "n8n-nodes-base.code",
        "typeVersion": 2,
        "position": [
          1500,
          300
        ],
        "parameters": {
          "jsCode": "const items = $input.all();\nconst allData = items[0]?.json?.data || [];\nconst jobs = allData.map(d => ({ asset_id: d.asset_id, job_id: d.job_id, status: d.status }));\n\nreturn [{\n  json: {\n    success: true,\n    message: `Triggered video generation for ${jobs.length} assets`,\n    jobs: jobs,\n    triggered_at: new Date().toISOString()\n  }\n}];"
        }
      },
      {
        "id": "respond",
        "name": "Respond",
        "type": "n8n-nodes-base.respondToWebhook",
        "typeVersion": 1.1,
        "position": [
          1700,
          300
        ],
        "parameters": {
          "respondWith": "json",
          "responseBody": "={{ $json }}"
        }
      },
      {
        "id": "no-assets-response",
        "name": "No Assets Response",
        "type": "n8n-nodes-base.respondToWebhook",
        "typeVersion": 1.1,
        "position": [
          900,
          500
        ],
        "parameters": {
          "respondWith": "json",
          "responseBody": "={{ { success: false, message: 'No video assets found for this plan' } }}"
        }
      }
    ],
    "connections": {
      "Webhook Trigger": {
        "main": [
          [
            {
              "node": "Get Plan Assets",
              "type": "main",
              "index": 0
            }
          ]
        ]
      },
      "Manual Trigger": {
        "main": [
          [
            {
              "node": "Get Plan Assets",
              "type": "main",
              "index": 0
            }
          ]
        ]
      },
      "Get Plan Assets": {
        "main": [
          [
            {
              "node": "Has Video Assets?",
              "type": "main",
              "index": 0
            }
          ]
        ]
      },
      "Has Video Assets?": {
        "main": [
          [
            {
              "node": "Build Job Payload",
              "type": "main",
              "index": 0
            }
          ],
          [
            {
              "node": "No Assets Response",
              "type": "main",
              "index": 0
            }
          ]
        ]
      },
      "Build Job Payload": {
        "main": [
          [
            {
              "node": "Trigger Job Gateway",
              "type": "main",
              "index": 0
            }
          ]
        ]
      },
      "Trigger Job Gateway": {
        "main": [
          [
            {
              "node": "Aggregate Results",
              "type": "main",
              "index": 0
            }
          ]
        ]
      },
      "Aggregate Results": {
        "main": [
          [
            {
              "node": "Format Response",
              "type": "main",
              "index": 0
            }
          ]
        ]
      },
      "Format Response": {
        "main": [
          [
            {
              "node": "Respond",
              "type": "main",
              "index": 0
            }
          ]
        ]
      }
    },
    "authors": "Kelly Knight",
    "name": null,
    "description": null,
    "autosaved": false
  },
  "tags": []
}